natug/__init__.py
natug/constants/__init__.py
natug/constants/bases.py
natug/constants/directions.py
natug/constants/switches.py
natug/constants/tabs.py
natug/constants/toolbar.py
natug/launcher.py
natug/runner/__init__.py
natug/runner/application.py
natug/runner/filehandler.py
natug/runner/managers/__init__.py
natug/runner/managers/domains.py
natug/runner/managers/double_helices.py
natug/runner/managers/manager.py
natug/runner/managers/managers.py
natug/runner/managers/misc.py
natug/runner/managers/nucleic_acid_profile.py
natug/runner/managers/snapshots.py
natug/runner/managers/strands.py
natug/runner/managers/toolbar.py
natug/runner/runner.py
natug/saves/domains/12-sigmagon.csv
natug/saves/domains/8-D-unclosed.csv
natug/saves/domains/heart.csv
natug/saves/domains/hexagon.csv
natug/saves/domains/hexagonB.csv
natug/saves/domains/nested.csv
natug/saves/domains/refactor.py
natug/saves/domains/regular_14gon.csv
natug/saves/domains/star.csv
natug/saves/domains/tengon.csv
natug/saves/domains/triangle.csv
natug/saves/nucleic_acid/MFD_B-DNA.json
natug/saves/nucleic_acid/Restored.json
natug/saves/strands/presets/m13mp18.txt
natug/settings.py
natug/structures/__init__.py
natug/structures/domains/__init__.py
natug/structures/domains/domain.py
natug/structures/domains/domains.py
natug/structures/domains/subunit.py
natug/structures/helices/__init__.py
natug/structures/helices/double_helices.py
natug/structures/helices/double_helix.py
natug/structures/helices/helix.py
natug/structures/misc/__init__.py
natug/structures/misc/save.py
natug/structures/points/__init__.py
natug/structures/points/nemid.py
natug/structures/points/nick.py
natug/structures/points/nucleoside.py
natug/structures/points/point.py
natug/structures/points/pseudo.py
natug/structures/profiles/__init__.py
natug/structures/profiles/action_repeater_profile.py
natug/structures/profiles/nucleic_acid_profile.py
natug/structures/strands/__init__.py
natug/structures/strands/linkage.py
natug/structures/strands/strand.py
natug-3.0.92.dist-info/METADATA
natug-3.0.92.dist-info/WHEEL
natug-3.0.92.dist-info/entry_points.txt
natug-3.0.92.dist-info/RECORD
