Metadata-Version: 2.1
Name: natug
Version: 3.0.92
Summary: Nucleic acid design desktop application
Author: Wolf Mermelstein
Author-email: wolfmermelstein@gmail.com
Requires-Python: >=3.10,<4.0
Classifier: Programming Language :: Python :: 3
Classifier: Programming Language :: Python :: 3.10
Classifier: Programming Language :: Python :: 3.11
Classifier: Programming Language :: Python :: 3.12
Requires-Dist: cairosvg (>=2.7.1,<3.0.0)
Requires-Dist: matplotlib (>=3.9.2,<4.0.0)
Requires-Dist: numpy (>=2.1.1,<3.0.0)
Requires-Dist: openpyxl (>=3.1.5,<4.0.0)
Requires-Dist: pandas (>=2.2.3,<3.0.0)
Requires-Dist: pyopengl (>=3.1.7,<4.0.0)
Requires-Dist: pyqt6 (>=6.7.1,<7.0.0)
Requires-Dist: pyqt6-qt6 (>=6.7.2,<7.0.0)
Requires-Dist: pyqt6-sip (>=13.8.0,<14.0.0)
Requires-Dist: pyqtgraph (>=0.13.7,<0.14.0)
Requires-Dist: show-in-file-manager (>=1.1.5,<2.0.0)
Requires-Dist: xlsxwriter (>=3.2.0,<4.0.0)
Requires-Dist: xlwt (>=1.3.0,<2.0.0)
